faciesteller/__init__.py
faciesteller/faciesteller.py
faciesteller-1.0.5.dist-info/LICENSE
faciesteller-1.0.5.dist-info/METADATA
faciesteller-1.0.5.dist-info/WHEEL
faciesteller-1.0.5.dist-info/top_level.txt
faciesteller-1.0.5.dist-info/RECORD
