Metadata-Version: 2.1
Name: faciesteller
Version: 1.0.5
Summary: This package is created to classify facies using FMI image and depth CSV data, output prediction result with csv format as well as image.
Home-page: UNKNOWN
Author: Xiaohu Jiang
License: UNKNOWN
Platform: UNKNOWN
Classifier: Programming Language :: Python :: 3
Classifier: License :: OSI Approved :: MIT License
Classifier: Operating System :: OS Independent
Requires-Dist: numpy (==1.24.2)
Requires-Dist: pandas (==1.5.3)
Requires-Dist: Pillow (==9.1.1)
Requires-Dist: tensorflow (==2.11.0)
